{
    "title": "Archives",
    "description": "",
    "link": "https://www.chambredesrepresentants.ma/ar",
    "image": "",
    "category": [],
    "items": [
        {
            "id": "https://www.chambredesrepresentants.ma/ar/110225",
            "title": "جلسة عمومية  لمناقشة عرض المجلس الأعلى للحسابات تليها جلسة لاختتام الدورة الثلاثاء 11 فبراير 2025",
            "description": "جلسة عمومية  لمناقشة عرض المجلس الأعلى للحسابات تليها جلسة لاختتام الدورة الثلاثاء 11 فبراير 2025",
            "link": "https://www.chambredesrepresentants.ma/ar/110225",
            "author": "Chambre des Représentants",
            "published": 1739264400000,
            "created": 1739264400000,
            "category": [],
            "enclosures": [],
            "media": {}
        },
        {
            "id": "https://www.chambredesrepresentants.ma/ar/100225",
            "title": "جلسة عمومية للأسئلة الشفوية الاثنين 10 فبراير 2025",
            "description": "جلسة عمومية للأسئلة الشفوية الاثنين 10 فبراير 2025",
            "link": "https://www.chambredesrepresentants.ma/ar/100225",
            "author": "Chambre des Représentants",
            "published": 1739196000000,
            "created": 1739196000000,
            "category": [],
            "enclosures": [],
            "media": {}
        },
        {
            "id": "https://www.chambredesrepresentants.ma/ar/050225",
            "title": "جلسة عمومية تشريعية الأربعاء 5 فبراير 2025",
            "description": "جلسة عمومية تشريعية الأربعاء 5 فبراير 2025",
            "link": "https://www.chambredesrepresentants.ma/ar/050225",
            "author": "Chambre des Représentants",
            "published": 1738746000000,
            "created": 1738746000000,
            "category": [],
            "enclosures": [],
            "media": {}
        },
        {
            "id": "https://www.chambredesrepresentants.ma/ar/%D9%85%D8%B0%D9%83%D8%B1%D8%A9/%D9%82%D8%B1%D8%A7%D8%A1%D8%A9-%D8%AB%D8%A7%D9%86%D9%8A%D8%A9-%D9%84%D9%85%D8%B4%D8%B1%D9%88%D8%B9-%D9%82%D8%A7%D9%86%D9%88%D9%86-%D8%AA%D9%86%D8%B8%D9%8A%D9%85%D9%8A-%D8%B1%D9%82%D9%85-9715-%D8%A7%D9%84%D8%AB%D9%84%D8%A7%D8%AB%D8%A7%D8%A1-4-%D9%81%D8%A8%D8%B1%D8%A7%D9%8A%D8%B1-2025",
            "title": "قراءة ثانية لمشروع قانون تنظيمي رقم 97.15 الثلاثاء 4 فبراير 2025",
            "description": "قراءة ثانية لمشروع قانون تنظيمي رقم 97.15 الثلاثاء 4 فبراير 2025",
            "link": "https://www.chambredesrepresentants.ma/ar/%D9%85%D8%B0%D9%83%D8%B1%D8%A9/%D9%82%D8%B1%D8%A7%D8%A1%D8%A9-%D8%AB%D8%A7%D9%86%D9%8A%D8%A9-%D9%84%D9%85%D8%B4%D8%B1%D9%88%D8%B9-%D9%82%D8%A7%D9%86%D9%88%D9%86-%D8%AA%D9%86%D8%B8%D9%8A%D9%85%D9%8A-%D8%B1%D9%82%D9%85-9715-%D8%A7%D9%84%D8%AB%D9%84%D8%A7%D8%AB%D8%A7%D8%A1-4-%D9%81%D8%A8%D8%B1%D8%A7%D9%8A%D8%B1-2025",
            "author": "Chambre des Représentants",
            "published": 1738684800000,
            "created": 1738684800000,
            "category": [],
            "enclosures": [],
            "media": {}
        },
        {
            "id": "https://www.chambredesrepresentants.ma/ar/%D9%85%D8%B0%D9%83%D8%B1%D8%A9/%D9%85%D9%86%D8%A7%D9%82%D8%B4%D8%A9-%D8%AA%D9%82%D8%B1%D9%8A%D8%B1-%D8%A7%D9%84%D9%85%D9%87%D9%85%D8%A9-%D8%A7%D9%84%D8%A7%D8%B3%D8%AA%D8%B7%D9%84%D8%A7%D8%B9%D9%8A%D8%A9-%D8%AD%D9%88%D9%84-%D8%A7%D9%84%D8%B7%D8%B1%D9%82-%D8%A7%D9%84%D8%B3%D9%8A%D8%A7%D8%B1%D8%A9-%D8%A7%D9%84%D8%AB%D9%84%D8%A7%D8%AB%D8%A7%D8%A1-4-%D9%81%D8%A8%D8%B1%D8%A7%D9%8A%D8%B1-2025",
            "title": "مناقشة تقرير المهمة الاستطلاعية حول الطرق السيارة الثلاثاء 4 فبراير 2025",
            "description": "مناقشة تقرير المهمة الاستطلاعية حول الطرق السيارة الثلاثاء 4 فبراير 2025",
            "link": "https://www.chambredesrepresentants.ma/ar/%D9%85%D8%B0%D9%83%D8%B1%D8%A9/%D9%85%D9%86%D8%A7%D9%82%D8%B4%D8%A9-%D8%AA%D9%82%D8%B1%D9%8A%D8%B1-%D8%A7%D9%84%D9%85%D9%87%D9%85%D8%A9-%D8%A7%D9%84%D8%A7%D8%B3%D8%AA%D8%B7%D9%84%D8%A7%D8%B9%D9%8A%D8%A9-%D8%AD%D9%88%D9%84-%D8%A7%D9%84%D8%B7%D8%B1%D9%82-%D8%A7%D9%84%D8%B3%D9%8A%D8%A7%D8%B1%D8%A9-%D8%A7%D9%84%D8%AB%D9%84%D8%A7%D8%AB%D8%A7%D8%A1-4-%D9%81%D8%A8%D8%B1%D8%A7%D9%8A%D8%B1-2025",
            "author": "Chambre des Représentants",
            "published": 1738679400000,
            "created": 1738679400000,
            "category": [],
            "enclosures": [],
            "media": {}
        },
        {
            "id": "https://www.chambredesrepresentants.ma/ar/%D9%85%D8%B0%D9%83%D8%B1%D8%A9/%D9%85%D8%AA%D8%A7%D8%A8%D8%B9%D8%A9-%D8%AF%D8%B1%D8%A7%D8%B3%D8%A9-%D9%85%D8%B4%D8%B1%D9%88%D8%B9-%D9%82%D8%A7%D9%86%D9%88%D9%86-%D8%B1%D9%82%D9%85-2723-%D8%A7%D9%84%D8%AB%D9%84%D8%A7%D8%AB%D8%A7%D8%A1-4-%D9%81%D8%A8%D8%B1%D8%A7%D9%8A%D8%B1-2025",
            "title": "متابعة دراسة مشروع قانون رقم 27.23 الثلاثاء 4 فبراير 2025",
            "description": "متابعة دراسة مشروع قانون رقم 27.23 الثلاثاء 4 فبراير 2025",
            "link": "https://www.chambredesrepresentants.ma/ar/%D9%85%D8%B0%D9%83%D8%B1%D8%A9/%D9%85%D8%AA%D8%A7%D8%A8%D8%B9%D8%A9-%D8%AF%D8%B1%D8%A7%D8%B3%D8%A9-%D9%85%D8%B4%D8%B1%D9%88%D8%B9-%D9%82%D8%A7%D9%86%D9%88%D9%86-%D8%B1%D9%82%D9%85-2723-%D8%A7%D9%84%D8%AB%D9%84%D8%A7%D8%AB%D8%A7%D8%A1-4-%D9%81%D8%A8%D8%B1%D8%A7%D9%8A%D8%B1-2025",
            "author": "Chambre des Représentants",
            "published": 1738677600000,
            "created": 1738677600000,
            "category": [],
            "enclosures": [],
            "media": {}
        },
        {
            "id": "https://www.chambredesrepresentants.ma/ar/%D9%85%D8%B0%D9%83%D8%B1%D8%A9/%D8%AA%D8%A3%D8%AC%D9%8A%D9%84-%D8%A7%D9%84%D9%85%D9%86%D8%A7%D9%82%D8%B4%D8%A9-%D8%A7%D9%84%D8%B9%D8%A7%D9%85%D8%A9-%D9%84%D9%85%D8%B4%D8%B1%D9%88%D8%B9-%D9%82%D8%A7%D9%86%D9%88%D9%86-%D8%B1%D9%82%D9%85-0323-%D8%A7%D9%84%D8%AB%D9%84%D8%A7%D8%AB%D8%A7%D8%A1%C2%A04-%D9%81%D8%A8%D8%B1%D8%A7%D9%8A%D8%B1-2025",
            "title": "**تأجيل** المناقشة العامة لمشروع قانون رقم 03.23 الثلاثاء 4 فبراير 2025",
            "description": "**تأجيل** المناقشة العامة لمشروع قانون رقم 03.23 الثلاثاء&nbsp;4 فبراير 2025",
            "link": "https://www.chambredesrepresentants.ma/ar/%D9%85%D8%B0%D9%83%D8%B1%D8%A9/%D8%AA%D8%A3%D8%AC%D9%8A%D9%84-%D8%A7%D9%84%D9%85%D9%86%D8%A7%D9%82%D8%B4%D8%A9-%D8%A7%D9%84%D8%B9%D8%A7%D9%85%D8%A9-%D9%84%D9%85%D8%B4%D8%B1%D9%88%D8%B9-%D9%82%D8%A7%D9%86%D9%88%D9%86-%D8%B1%D9%82%D9%85-0323-%D8%A7%D9%84%D8%AB%D9%84%D8%A7%D8%AB%D8%A7%D8%A1%C2%A04-%D9%81%D8%A8%D8%B1%D8%A7%D9%8A%D8%B1-2025",
            "author": "Chambre des Représentants",
            "published": 1738677600000,
            "created": 1738677600000,
            "category": [],
            "enclosures": [],
            "media": {}
        },
        {
            "id": "https://www.chambredesrepresentants.ma/ar/%D9%85%D8%B0%D9%83%D8%B1%D8%A9/%D8%A7%D8%AC%D8%AA%D9%85%D8%A7%D8%B9-%D9%85%D9%83%D8%AA%D8%A8-%D9%84%D8%AC%D9%86%D8%A9-%D8%A7%D9%84%D8%A8%D9%86%D9%8A%D8%A7%D8%AA-%D8%A7%D9%84%D8%A3%D8%B3%D8%A7%D8%B3%D9%8A%D8%A9%C2%A0%D8%A7%D9%84%D8%AB%D9%84%D8%A7%D8%AB%D8%A7%D8%A1%C2%A04-%D9%81%D8%A8%D8%B1%D8%A7%D9%8A%D8%B1-2025",
            "title": "اجتماع مكتب لجنة البنيات الأساسية الثلاثاء 4 فبراير 2025",
            "description": "اجتماع مكتب لجنة البنيات الأساسية&nbsp;الثلاثاء&nbsp;4 فبراير 2025",
            "link": "https://www.chambredesrepresentants.ma/ar/%D9%85%D8%B0%D9%83%D8%B1%D8%A9/%D8%A7%D8%AC%D8%AA%D9%85%D8%A7%D8%B9-%D9%85%D9%83%D8%AA%D8%A8-%D9%84%D8%AC%D9%86%D8%A9-%D8%A7%D9%84%D8%A8%D9%86%D9%8A%D8%A7%D8%AA-%D8%A7%D9%84%D8%A3%D8%B3%D8%A7%D8%B3%D9%8A%D8%A9%C2%A0%D8%A7%D9%84%D8%AB%D9%84%D8%A7%D8%AB%D8%A7%D8%A1%C2%A04-%D9%81%D8%A8%D8%B1%D8%A7%D9%8A%D8%B1-2025",
            "author": "Chambre des Représentants",
            "published": 1738675800000,
            "created": 1738675800000,
            "category": [],
            "enclosures": [],
            "media": {}
        },
        {
            "id": "https://www.chambredesrepresentants.ma/ar/%D9%85%D8%B0%D9%83%D8%B1%D8%A9/%D8%AA%D9%82%D8%AF%D9%8A%D9%85-%D8%AF%D8%B1%D8%A7%D8%B3%D8%A9-%D8%AD%D9%88%D9%84-%D8%A7%D9%84%D8%AA%D8%AF%D8%A8%D9%8A%D8%B1-%D8%A7%D9%84%D8%A3%D9%85%D9%86%D9%8A-%D9%84%D9%84%D8%B9%D9%86%D9%81-%D9%88%D8%A3%D8%AD%D8%AF%D8%A7%D8%AB-%D8%A7%D9%84%D8%B4%D8%BA%D8%A8-%D8%A8%D8%A7%D9%84%D9%85%D9%84%D8%A7%D8%B9%D8%A8-%D8%A7%D9%84%D8%B1%D9%8A%D8%A7%D8%B6%D9%8A%D8%A9-%D8%A7%D9%84%D8%AB%D9%84%D8%A7%D8%AB%D8%A7%D8%A1-4-%D9%81%D8%A8%D8%B1%D8%A7%D9%8A%D8%B1-2025",
            "title": "تقديم دراسة حول التدبير الأمني للعنف وأحداث الشغب بالملاعب الرياضية الثلاثاء 4 فبراير 2025",
            "description": "تقديم دراسة حول التدبير الأمني للعنف وأحداث الشغب بالملاعب الرياضية الثلاثاء 4 فبراير 2025",
            "link": "https://www.chambredesrepresentants.ma/ar/%D9%85%D8%B0%D9%83%D8%B1%D8%A9/%D8%AA%D9%82%D8%AF%D9%8A%D9%85-%D8%AF%D8%B1%D8%A7%D8%B3%D8%A9-%D8%AD%D9%88%D9%84-%D8%A7%D9%84%D8%AA%D8%AF%D8%A8%D9%8A%D8%B1-%D8%A7%D9%84%D8%A3%D9%85%D9%86%D9%8A-%D9%84%D9%84%D8%B9%D9%86%D9%81-%D9%88%D8%A3%D8%AD%D8%AF%D8%A7%D8%AB-%D8%A7%D9%84%D8%B4%D8%BA%D8%A8-%D8%A8%D8%A7%D9%84%D9%85%D9%84%D8%A7%D8%B9%D8%A8-%D8%A7%D9%84%D8%B1%D9%8A%D8%A7%D8%B6%D9%8A%D8%A9-%D8%A7%D9%84%D8%AB%D9%84%D8%A7%D8%AB%D8%A7%D8%A1-4-%D9%81%D8%A8%D8%B1%D8%A7%D9%8A%D8%B1-2025",
            "author": "Chambre des Représentants",
            "published": 1738674000000,
            "created": 1738674000000,
            "category": [],
            "enclosures": [],
            "media": {}
        },
        {
            "id": "https://www.chambredesrepresentants.ma/ar/%D9%85%D8%B0%D9%83%D8%B1%D8%A9/%D8%AA%D9%82%D8%AF%D9%8A%D9%85-%D8%B9%D8%B1%D8%B6-%D8%B9%D8%A7%D9%85-%D8%AD%D9%88%D9%84-%D8%A7%D9%84%D8%A8%D9%86%D9%8A%D8%A7%D8%AA-%D8%A7%D9%84%D8%AA%D8%AD%D8%AA%D9%8A%D8%A9-%D8%A7%D9%84%D8%B1%D9%8A%D8%A7%D8%B6%D9%8A%D8%A9-%D8%A7%D9%84%D8%AB%D9%84%D8%A7%D8%AB%D8%A7%D8%A1-4-%D9%81%D8%A8%D8%B1%D8%A7%D9%8A%D8%B1-2025",
            "title": "تقديم عرض عام حول البنيات التحتية الرياضية الثلاثاء 4 فبراير 2025",
            "description": "تقديم عرض عام حول البنيات التحتية الرياضية الثلاثاء 4 فبراير 2025",
            "link": "https://www.chambredesrepresentants.ma/ar/%D9%85%D8%B0%D9%83%D8%B1%D8%A9/%D8%AA%D9%82%D8%AF%D9%8A%D9%85-%D8%B9%D8%B1%D8%B6-%D8%B9%D8%A7%D9%85-%D8%AD%D9%88%D9%84-%D8%A7%D9%84%D8%A8%D9%86%D9%8A%D8%A7%D8%AA-%D8%A7%D9%84%D8%AA%D8%AD%D8%AA%D9%8A%D8%A9-%D8%A7%D9%84%D8%B1%D9%8A%D8%A7%D8%B6%D9%8A%D8%A9-%D8%A7%D9%84%D8%AB%D9%84%D8%A7%D8%AB%D8%A7%D8%A1-4-%D9%81%D8%A8%D8%B1%D8%A7%D9%8A%D8%B1-2025",
            "author": "Chambre des Représentants",
            "published": 1738663200000,
            "created": 1738663200000,
            "category": [],
            "enclosures": [],
            "media": {}
        }
    ]
}