{
    "title": "News",
    "description": "",
    "link": "https://www.chambredesrepresentants.ma/ar",
    "image": "",
    "category": [],
    "items": [
        {
            "id": "ورشة عمل حول \"الذكاء الاصطناعي والمجتمع\" الخميس 23 يناير 2025",
            "title": "ورشة عمل حول \"الذكاء الاصطناعي والمجتمع\" الخميس 23 يناير 2025",
            "description": "نظمت مجموعة العمل الموضوعاتية المؤقتة حول \"الذكاء الاصطناعي: آفاقه وتأثيراته\"، ورشة عمل في موضوع \"الذكاء الاصطناعي والمجتمع: الاعتبارات الاقتصادية والاجتماعية والرهانات الأخلاقية \"، يوم الخميس 23 يناير 2025 على الساعة التاسعة والنصف صباحا، برآسة السيد أنوار صبري، رئيس المجموعة الموضوعاتية، وحضور…",
            "link": "https://www.chambredesrepresentants.ma/%3Ca%20href%3D%22/ar/%25D8%25A3%25D8%25AE%25D8%25A8%25D8%25A7%25D8%25B1/%25D9%2588%25D8%25B1%25D8%25B4%25D8%25A9-%25D8%25B9%25D9%2585%25D9%2584-%25D8%25AD%25D9%2588%25D9%2584-%25D8%25A7%25D9%2584%25D8%25B0%25D9%2583%25D8%25A7%25D8%25A1-%25D8%25A7%25D9%2584%25D8%25A7%25D8%25B5%25D8%25B7%25D9%2586%25D8%25A7%25D8%25B9%25D9%258A-%25D9%2588%25D8%25A7%25D9%2584%25D9%2585%25D8%25AC%25D8%25AA%25D9%2585%25D8%25B9-%25D8%25A7%25D9%2584%25D8%25AE%25D9%2585%25D9%258A%25D8%25B3-23-%25D9%258A%25D9%2586%25D8%25A7%25D9%258A%25D8%25B1-2025%22%20hreflang%3D%22ar%22%3Evoir%3C/a%3E",
            "author": "rajae",
            "published": 1737633600000,
            "created": 1737633600000,
            "category": [],
            "enclosures": [],
            "media": {}
        },
        {
            "id": "ورشة عمل حول \"التقائية الجهود والرؤى لتطوير ذكاء اصطناعي مسؤول ومستدام\" الخميس 23 يناير 2025",
            "title": "ورشة عمل حول \"التقائية الجهود والرؤى لتطوير ذكاء اصطناعي مسؤول ومستدام\" الخميس 23 يناير 2025",
            "description": "نظمت مجموعة العمل الموضوعاتية المؤقتة حول \"الذكاء الاصطناعي: آفاقه وتأثيراته\"، ورشة عمل في موضوع \"التقائية الجهود والرؤى لتطوير ذكاء اصطناعي مسؤول ومستدام\"، يوم الخميس 23 يناير 2025 على الساعة الثانية بعد الزوال، برآسة السيد أنوار صبري، رئيس المجموعة الموضوعاتية، وحضور السيدات النائبات والسادة…",
            "link": "https://www.chambredesrepresentants.ma/%3Ca%20href%3D%22/ar/%25D8%25A3%25D8%25AE%25D8%25A8%25D8%25A7%25D8%25B1/%25D9%2588%25D8%25B1%25D8%25B4%25D8%25A9-%25D8%25B9%25D9%2585%25D9%2584-%25D8%25AD%25D9%2588%25D9%2584-%25D8%25A7%25D9%2584%25D8%25AA%25D9%2582%25D8%25A7%25D8%25A6%25D9%258A%25D8%25A9-%25D8%25A7%25D9%2584%25D8%25AC%25D9%2587%25D9%2588%25D8%25AF-%25D9%2588%25D8%25A7%25D9%2584%25D8%25B1%25D8%25A4%25D9%2589-%25D9%2584%25D8%25AA%25D8%25B7%25D9%2588%25D9%258A%25D8%25B1-%25D8%25B0%25D9%2583%25D8%25A7%25D8%25A1-%25D8%25A7%25D8%25B5%25D8%25B7%25D9%2586%25D8%25A7%25D8%25B9%25D9%258A-%25D9%2585%25D8%25B3%25D8%25A4%25D9%2588%25D9%2584-%25D9%2588%25D9%2585%25D8%25B3%25D8%25AA%25D8%25AF%25D8%25A7%25D9%2585-%25D8%25A7%25D9%2584%25D8%25AE%25D9%2585%25D9%258A%25D8%25B3-23-%25D9%258A%25D9%2586%25D8%25A7%25D9%258A%25D8%25B1-2025%22%20hreflang%3D%22ar%22%3Evoir%3C/a%3E",
            "author": "rajae",
            "published": 1737633600000,
            "created": 1737633600000,
            "category": [],
            "enclosures": [],
            "media": {}
        },
        {
            "id": "رئيسا مجلس النواب والجمعية الوطنية الفيتنامية يؤكدان أهمية تعزيز التعاون والتنسيق البرلمانيين وتبادل الخبرات في إطار احترام سيادة الدول ووحدتها الترابية",
            "title": "رئيسا مجلس النواب والجمعية الوطنية الفيتنامية يؤكدان أهمية تعزيز التعاون والتنسيق البرلمانيين وتبادل الخبرات في إطار احترام سيادة الدول ووحدتها الترابية",
            "description": "أجرى رئيس مجلس النواب السيد راشيد الطالبي العلمي، يوم الثلاثاء 21 يناير الجاري في مدينة \" كان ثو\" بجمهورية الفيتنام الاشتراكية، لقائين ثنائيين مع كل من السيد&nbsp;Tran Thanh Man رئيس الجمعية الوطنية ومع السيد&nbsp; &nbsp;Minh Hoan Lê وزير الفلاحة والتنمية القروية، وذلك بمناسبة أشغال الجمعية…",
            "link": "https://www.chambredesrepresentants.ma/%3Ca%20href%3D%22/ar/Talbi220125%22%20hreflang%3D%22ar%22%3Evoir%3C/a%3E",
            "author": "rajae",
            "published": 1737547200000,
            "created": 1737547200000,
            "category": [],
            "enclosures": [],
            "media": {}
        },
        {
            "id": "مذكرة تتعلق باجتماع لجنة القطاعات الاجتماعية ليوم الثلاثاء 21 يناير 2025 للبت والتصويت على مقترحين",
            "title": "مذكرة تتعلق باجتماع لجنة القطاعات الاجتماعية ليوم الثلاثاء 21 يناير 2025 للبت والتصويت على مقترحين",
            "description": "عقدت لجنة القطاعات الاجتماعية يوم الثلاثاء 21 يناير 2025 اجتماعا على الساعة العاشرة والنصف صباحا، خصص للبت والتصويت على مقترح قانون بتغيير وتتميم الظهير الشريف بمثابة قانون رقم 1.72.184 المتعلق بنظام الضمان الاجتماعي، والبت والتصويت على مقترح قانون يقضي بتغيير وتتميم الظهير الشريف بمثابة قانون رقم…",
            "link": "https://www.chambredesrepresentants.ma/%3Ca%20href%3D%22/ar/%25D8%25A3%25D8%25AE%25D8%25A8%25D8%25A7%25D8%25B1/%25D9%2585%25D8%25B0%25D9%2583%25D8%25B1%25D8%25A9-%25D8%25AA%25D8%25AA%25D8%25B9%25D9%2584%25D9%2582-%25D8%25A8%25D8%25A7%25D8%25AC%25D8%25AA%25D9%2585%25D8%25A7%25D8%25B9-%25D9%2584%25D8%25AC%25D9%2586%25D8%25A9-%25D8%25A7%25D9%2584%25D9%2582%25D8%25B7%25D8%25A7%25D8%25B9%25D8%25A7%25D8%25AA-%25D8%25A7%25D9%2584%25D8%25A7%25D8%25AC%25D8%25AA%25D9%2585%25D8%25A7%25D8%25B9%25D9%258A%25D8%25A9-%25D9%2584%25D9%258A%25D9%2588%25D9%2585-%25D8%25A7%25D9%2584%25D8%25AB%25D9%2584%25D8%25A7%25D8%25AB%25D8%25A7%25D8%25A1-21-%25D9%258A%25D9%2586%25D8%25A7%25D9%258A%25D8%25B1-2025-%25D9%2584%25D9%2584%25D8%25A8%25D8%25AA-%25D9%2588%25D8%25A7%25D9%2584%25D8%25AA%25D8%25B5%25D9%2588%25D9%258A%25D8%25AA-%25D8%25B9%25D9%2584%25D9%2589%22%20hreflang%3D%22ar%22%3Evoir%3C/a%3E",
            "author": "rajae",
            "published": 1737547200000,
            "created": 1737547200000,
            "category": [],
            "enclosures": [],
            "media": {}
        },
        {
            "id": "ورشة عمل حول الإطار التشريعي والتنظيمي للذكاء الاصطناعي بالمغرب الأربعاء 22 يناير 2025",
            "title": "ورشة عمل حول الإطار التشريعي والتنظيمي للذكاء الاصطناعي بالمغرب الأربعاء 22 يناير 2025",
            "description": "تنظمت مجموعة العمل الموضوعاتية المؤقتة حول \"الذكاء الاصطناعي: آفاقه و تأثيراته\"، ورشة عمل في موضوع \"الإطار التشريعي والتنظيمي للذكاء الاصطناعي بالمغرب، وآفاق استخدامه في العمل البرلماني\"، يوم الأربعاء 22 يناير 2025 على الساعة التاسعة والنصف صباحا، برآسة السيد أنوار صبري، رئيس المجموعة الموضوعاتية،…",
            "link": "https://www.chambredesrepresentants.ma/%3Ca%20href%3D%22/ar/%25D8%25A3%25D8%25AE%25D8%25A8%25D8%25A7%25D8%25B1/%25D9%2588%25D8%25B1%25D8%25B4%25D8%25A9-%25D8%25B9%25D9%2585%25D9%2584-%25D8%25AD%25D9%2588%25D9%2584-%25D8%25A7%25D9%2584%25D8%25A5%25D8%25B7%25D8%25A7%25D8%25B1-%25D8%25A7%25D9%2584%25D8%25AA%25D8%25B4%25D8%25B1%25D9%258A%25D8%25B9%25D9%258A-%25D9%2588%25D8%25A7%25D9%2584%25D8%25AA%25D9%2586%25D8%25B8%25D9%258A%25D9%2585%25D9%258A-%25D9%2584%25D9%2584%25D8%25B0%25D9%2583%25D8%25A7%25D8%25A1-%25D8%25A7%25D9%2584%25D8%25A7%25D8%25B5%25D8%25B7%25D9%2586%25D8%25A7%25D8%25B9%25D9%258A-%25D8%25A8%25D8%25A7%25D9%2584%25D9%2585%25D8%25BA%25D8%25B1%25D8%25A8-%25D8%25A7%25D9%2584%25D8%25A3%25D8%25B1%25D8%25A8%25D8%25B9%25D8%25A7%25D8%25A1-22-%25D9%258A%25D9%2586%25D8%25A7%25D9%258A%25D8%25B1-2025%22%20hreflang%3D%22ar%22%3Evoir%3C/a%3E",
            "author": "rajae",
            "published": 1737547200000,
            "created": 1737547200000,
            "category": [],
            "enclosures": [],
            "media": {}
        },
        {
            "id": "مذكرة تتعلق باجتماع لجنة القطاعات الاجتماعية ليوم الثلاثاء 21 يناير 2025 للبت والتصويت على مشروع قانون رقم 02.24",
            "title": "مذكرة تتعلق باجتماع لجنة القطاعات الاجتماعية ليوم الثلاثاء 21 يناير 2025 للبت والتصويت على مشروع قانون رقم 02.24",
            "description": "عقدت لجنة القطاعات الاجتماعية يوم الثلاثاء 21 يناير 2025&nbsp; اجتماعا خصص للبت والتصويت على&nbsp; مشروع قانون رقم 02.24 بتغيير وتتميم الظهير الشريف بمثابة قانون رقم 1.72.184 بتاريخ 15 من جمادى الآخرة 1392 (27 يوليو 1972) المتعلق بنظام الضمان الاجتماعي، محال من مجلس المستشارين، ترأسه السيد حميد…",
            "link": "https://www.chambredesrepresentants.ma/%3Ca%20href%3D%22/ar/%25D8%25A3%25D8%25AE%25D8%25A8%25D8%25A7%25D8%25B1/%25D9%2585%25D8%25B0%25D9%2583%25D8%25B1%25D8%25A9-%25D8%25AA%25D8%25AA%25D8%25B9%25D9%2584%25D9%2582-%25D8%25A8%25D8%25A7%25D8%25AC%25D8%25AA%25D9%2585%25D8%25A7%25D8%25B9-%25D9%2584%25D8%25AC%25D9%2586%25D8%25A9-%25D8%25A7%25D9%2584%25D9%2582%25D8%25B7%25D8%25A7%25D8%25B9%25D8%25A7%25D8%25AA-%25D8%25A7%25D9%2584%25D8%25A7%25D8%25AC%25D8%25AA%25D9%2585%25D8%25A7%25D8%25B9%25D9%258A%25D8%25A9-%25D9%2584%25D9%258A%25D9%2588%25D9%2585-%25D8%25A7%25D9%2584%25D8%25AB%25D9%2584%25D8%25A7%25D8%25AB%25D8%25A7%25D8%25A1-21-%25D9%258A%25D9%2586%25D8%25A7%25D9%258A%25D8%25B1-2025-%25D9%2584%25D9%2584%25D8%25A8%25D8%25AA-%25D9%2588%25D8%25A7%25D9%2584%25D8%25AA%25D8%25B5%25D9%2588%25D9%258A%25D8%25AA-%25D8%25B9%25D9%2584%25D9%2589-0%22%20hreflang%3D%22ar%22%3Evoir%3C/a%3E",
            "author": "rajae",
            "published": 1737547200000,
            "created": 1737547200000,
            "category": [],
            "enclosures": [],
            "media": {}
        },
        {
            "id": "ورشة عمل حول \"الذكاء الاصطناعي بين المتطلبات والآفاق\" الأربعاء 22 يناير 2025",
            "title": "ورشة عمل حول \"الذكاء الاصطناعي بين المتطلبات والآفاق\" الأربعاء 22 يناير 2025",
            "description": "نظمت مجموعة العمل الموضوعاتية المؤقتة حول \"الذكاء الاصطناعي: آفاقه و تأثيراته\"، ورشة عمل في موضوع \"الذكاء الاصطناعي بين المتطلبات والآفاق: جاهزية البنى التحتية والتطوير التكنولوجي، بناء المهارات وتطوير البحث العلمي \"، يوم الأربعاء 22 يناير 2025 الأربعاء 22 يناير 2025 على الساعة الثانية بعد الزوال،…",
            "link": "https://www.chambredesrepresentants.ma/%3Ca%20href%3D%22/ar/%25D8%25A3%25D8%25AE%25D8%25A8%25D8%25A7%25D8%25B1/%25D9%2588%25D8%25B1%25D8%25B4%25D8%25A9-%25D8%25B9%25D9%2585%25D9%2584-%25D8%25AD%25D9%2588%25D9%2584-%25D8%25A7%25D9%2584%25D8%25B0%25D9%2583%25D8%25A7%25D8%25A1-%25D8%25A7%25D9%2584%25D8%25A7%25D8%25B5%25D8%25B7%25D9%2586%25D8%25A7%25D8%25B9%25D9%258A-%25D8%25A8%25D9%258A%25D9%2586-%25D8%25A7%25D9%2584%25D9%2585%25D8%25AA%25D8%25B7%25D9%2584%25D8%25A8%25D8%25A7%25D8%25AA-%25D9%2588%25D8%25A7%25D9%2584%25D8%25A2%25D9%2581%25D8%25A7%25D9%2582-%25D8%25A7%25D9%2584%25D8%25A3%25D8%25B1%25D8%25A8%25D8%25B9%25D8%25A7%25D8%25A1-22-%25D9%258A%25D9%2586%25D8%25A7%25D9%258A%25D8%25B1-2025%22%20hreflang%3D%22ar%22%3Evoir%3C/a%3E",
            "author": "rajae",
            "published": 1737547200000,
            "created": 1737547200000,
            "category": [],
            "enclosures": [],
            "media": {}
        },
        {
            "id": "مذكرة حول اجتماع لجنة التعليم والثقافة والاتصال للمناقشة العامة والتفصيلية لمشروع قانون رقم 33.22 يتعلق بحماية التراث",
            "title": "مذكرة حول اجتماع لجنة التعليم والثقافة والاتصال للمناقشة العامة والتفصيلية لمشروع قانون رقم 33.22 يتعلق بحماية التراث",
            "description": "عقدت لجنة التعليم والثقافة والاتصال، اجتماعا برئاسة النائب السيد عدي شجري، رئيس اللجنة وبحضور السيد محمد مهدي بنسعيد، وزير الشباب والثقافة والتواصل، يوم&nbsp; الأربعاء 22 يناير&nbsp; 2025&nbsp; ابتداء من الساعة العاشرة صباحا، بالقاعة رقم 08، خصص&nbsp; للمناقشة العامة والتفصيلية لمشروع قانون رقم 33.…",
            "link": "https://www.chambredesrepresentants.ma/%3Ca%20href%3D%22/ar/%25D8%25A3%25D8%25AE%25D8%25A8%25D8%25A7%25D8%25B1/%25D9%2585%25D8%25B0%25D9%2583%25D8%25B1%25D8%25A9-%25D8%25AD%25D9%2588%25D9%2584-%25D8%25A7%25D8%25AC%25D8%25AA%25D9%2585%25D8%25A7%25D8%25B9-%25D9%2584%25D8%25AC%25D9%2586%25D8%25A9-%25D8%25A7%25D9%2584%25D8%25AA%25D8%25B9%25D9%2584%25D9%258A%25D9%2585-%25D9%2588%25D8%25A7%25D9%2584%25D8%25AB%25D9%2582%25D8%25A7%25D9%2581%25D8%25A9-%25D9%2588%25D8%25A7%25D9%2584%25D8%25A7%25D8%25AA%25D8%25B5%25D8%25A7%25D9%2584-%25D9%2584%25D9%2584%25D9%2585%25D9%2586%25D8%25A7%25D9%2582%25D8%25B4%25D8%25A9-%25D8%25A7%25D9%2584%25D8%25B9%25D8%25A7%25D9%2585%25D8%25A9-%25D9%2588%25D8%25A7%25D9%2584%25D8%25AA%25D9%2581%25D8%25B5%25D9%258A%25D9%2584%25D9%258A%25D8%25A9-%25D9%2584%25D9%2585%25D8%25B4%25D8%25B1%25D9%2588%25D8%25B9-%25D9%2582%25D8%25A7%25D9%2586%25D9%2588%25D9%2586-%25D8%25B1%25D9%2582%25D9%2585-0%22%20hreflang%3D%22ar%22%3Evoir%3C/a%3E",
            "author": "rajae",
            "published": 1737547200000,
            "created": 1737547200000,
            "category": [],
            "enclosures": [],
            "media": {}
        },
        {
            "id": "النائب الأول لرئيس مجلس النواب السيد محمد صباري يجري مباحثات مع وفد عن لجنة الشؤون الخارجية بمجلس النواب الإيطالي",
            "title": "النائب الأول لرئيس مجلس النواب السيد محمد صباري يجري مباحثات مع وفد عن لجنة الشؤون الخارجية بمجلس النواب الإيطالي",
            "description": "أجرى النائب الأول لرئيس مجلس النواب السيد محمد صباري يوم الثلاثاء 21 يناير 2025 بمقر المجلس بالرباط، مباحثات مع وفد عن لجنة الشؤون الخارجية بمجلس النواب الإيطالي يقوم حاليا بزيارة عمل للمملكة المغربية.وبالمناسبة، أكد السيد محمد صباري ان المغرب وإيطاليا تجمعهما علاقات متميزة تسير وفق التوجيهات…",
            "link": "https://www.chambredesrepresentants.ma/%3Ca%20href%3D%22/ar/Sabbari210125%22%20hreflang%3D%22ar%22%3Evoir%3C/a%3E",
            "author": "rajae",
            "published": 1737460800000,
            "created": 1737460800000,
            "category": [],
            "enclosures": [],
            "media": {}
        },
        {
            "id": "مذكرة حول اجتماع لجنة البنيات الأساسية والطاقة والمعادن والبيئة والتنمية المستدامة الثلاثاء 21 يناير 2025",
            "title": "مذكرة حول اجتماع لجنة البنيات الأساسية والطاقة والمعادن والبيئة والتنمية المستدامة الثلاثاء 21 يناير 2025",
            "description": "* جدول أعمال: دراسة المواضيع التالية:﻿﻿إشكاليات النقل بالعالم القروي والجبلي وسبل تأهيله والارتقاء به (الفريقالحركي)؛﻿﻿استراتيجية تأهيل النقل بمختلف أصنافه في أفق الرهانات التي تنتظر بلادنا (الفريق الحركي)؛﻿﻿إصلاح قطاع النقل وتأهيله وزيادة جاذبيته وتنافسيته؛ منظومة النقل بالوسط القروي والمناطق…",
            "link": "https://www.chambredesrepresentants.ma/%3Ca%20href%3D%22/ar/%25D8%25A3%25D8%25AE%25D8%25A8%25D8%25A7%25D8%25B1/%25D9%2585%25D8%25B0%25D9%2583%25D8%25B1%25D8%25A9-%25D8%25AD%25D9%2588%25D9%2584-%25D8%25A7%25D8%25AC%25D8%25AA%25D9%2585%25D8%25A7%25D8%25B9-%25D9%2584%25D8%25AC%25D9%2586%25D8%25A9-%25D8%25A7%25D9%2584%25D8%25A8%25D9%2586%25D9%258A%25D8%25A7%25D8%25AA-%25D8%25A7%25D9%2584%25D8%25A3%25D8%25B3%25D8%25A7%25D8%25B3%25D9%258A%25D8%25A9-%25D9%2588%25D8%25A7%25D9%2584%25D8%25B7%25D8%25A7%25D9%2582%25D8%25A9-%25D9%2588%25D8%25A7%25D9%2584%25D9%2585%25D8%25B9%25D8%25A7%25D8%25AF%25D9%2586-%25D9%2588%25D8%25A7%25D9%2584%25D8%25A8%25D9%258A%25D8%25A6%25D8%25A9-%25D9%2588%25D8%25A7%25D9%2584%25D8%25AA%25D9%2586%25D9%2585%25D9%258A%25D8%25A9-%25D8%25A7%25D9%2584%25D9%2585%25D8%25B3%25D8%25AA%25D8%25AF%25D8%25A7%25D9%2585%25D8%25A9-%25D8%25A7%25D9%2584%25D8%25AB%25D9%2584%25D8%25A7%25D8%25AB%25D8%25A7%25D8%25A1-0%22%20hreflang%3D%22ar%22%3Evoir%3C/a%3E",
            "author": "rajae",
            "published": 1737460800000,
            "created": 1737460800000,
            "category": [],
            "enclosures": [],
            "media": {}
        }
    ]
}